[
  {
    "id": "show-20260515",
    "artistId": "artist-keithjohns",
    "artistName": "Keith Johns",
    "date": "2026-05-15",
    "startTime": "8pm",
    "genre": "Singer/Songwriter",
    "description": "Miami-raised singer-songwriter delivering emotionally resonant storytelling — soulful, honest lyrics that shift from joyful to introspective. Beautifully layered indie folk with hints of R&B soul.",
    "ticketLink": "https://www.keithjohnsmusic.com",
    "coverCharge": "Free",
    "featured": true,
    "status": "published"
  },
  {
    "id": "show-20260518",
    "artistId": "artist-blueroomquartet",
    "artistName": "The Blue Room Quartet",
    "date": "2026-05-18",
    "startTime": "8pm",
    "genre": "Live Jazz",
    "description": "A four-piece jazz ensemble bringing standards and originals to the Alton Road room.",
    "ticketLink": "",
    "coverCharge": "Free",
    "featured": true,
    "status": "published"
  },
  {
    "id": "show-20260522",
    "artistId": "artist-elianaruiz",
    "artistName": "Eliana Ruiz",
    "date": "2026-05-22",
    "startTime": "8pm",
    "genre": "Solo Guitar & Vocals",
    "description": "Miami-based singer-songwriter blending Latin folk with soul.",
    "ticketLink": "",
    "coverCharge": "Free",
    "featured": false,
    "status": "published"
  },
  {
    "id": "show-20260525",
    "artistId": "artist-altonroadblues",
    "artistName": "The Alton Road Blues Band",
    "date": "2026-05-25",
    "startTime": "8pm",
    "genre": "Blues",
    "description": "Classic electric blues — three-piece, loud in all the right ways.",
    "ticketLink": "https://www.instagram.com/stormymondaymia/",
    "coverCharge": "Free",
    "featured": true,
    "status": "published"
  },
  {
    "id": "show-20260529",
    "artistId": "artist-keithjohns",
    "artistName": "Keith Johns",
    "date": "2026-05-29",
    "startTime": "8pm",
    "genre": "Singer/Songwriter",
    "description": "Miami-raised singer-songwriter delivering emotionally resonant storytelling — soulful, honest lyrics that shift from joyful to introspective. Beautifully layered indie folk with hints of R&B soul.",
    "ticketLink": "https://www.keithjohnsmusic.com",
    "coverCharge": "Free",
    "featured": false,
    "status": "published"
  }
]
